aoc_toolbox-2023.12.5.2.dist-info/METADATA
aoc_toolbox-2023.12.5.2.dist-info/WHEEL
aoc_toolbox/__init__.py
aoc_toolbox/intmachine/__init__.py
aoc_toolbox/split/__init__.py
aoc_toolbox-2023.12.5.2.dist-info/RECORD
